Workbook
Name aporte: App!$D$21
Name patrimonio: App!$D$24
Name qtd_anos: App!$D$22
Name rendimento_carteira: App!$D$17
Name salario: App!$D$16
Name sugestao_investimento: App!$B$18
Name taxa_mensal: App!$D$23
Name valor_sugerido: App!$C$35

Sheet Perguntas De Negócio
B2: Este projeto tem o foco de desenvolver uma ferramenta a qual auxilie pessoas que desejam investir em fundos imobiliarios
B4: Perguntas de Negócio
B6: Quanto investir por mês?
B7: Por quantos anos?
B8: Taxa de rendimento mensal?
B9: Patrimônio acumulado?
B10: Dividendos mensais?

Sheet App
B15: CONFIGURAÇÕES
B16: Salário | D16: 5000
B17: Rendimento Carteira | D17: 0.009
B18: Sugestão de Investimento (30%) | D18: =salario*30% -> 1500
B20: INVESTIMENTO MENSAL
B21: Quanto investir por mês? | D21: 500
B22: Por quantos anos? | D22: 5
B23: Taxa de rendimento mensal? | D23: 0.01079
B24: Patrimônio acumulado? | D24: =FV(taxa_mensal,qtd_anos*12,aporte*-1) -> 41888.457
B25: Dividendos mensais? | D25: =patrimonio*rendimento_carteira -> 376.99611
B27: Cenários | D27: Dividendo
A28: 2 | B28: Quanto em 2 anos? | C28: =FV($D$23,$A28*12,$D$21*-1) -> 13613.814 | D28: =C28*rendimento_carteira -> 122.52432
A29: 5 | B29: Quanto em 5 anos? | C29: =FV($D$23,$A29*12,$D$21*-1) -> 41888.457 | D29: =C29*rendimento_carteira -> 376.99611
A30: 10 | B30: Quanto em 10 anos? | C30: =FV($D$23,$A30*12,$D$21*-1) -> 121642.11 | D30: =C30*rendimento_carteira -> 1094.779
A31: 20 | B31: Quanto em 20 anos? | C31: =FV($D$23,$A31*12,$D$21*-1) -> 562599.2 | D31: =C31*rendimento_carteira -> 5063.3928
A32: 30 | B32: Quanto em 30 anos? | C32: =FV($D$23,$A32*12,$D$21*-1) -> 2161084.8 | D32: =C32*rendimento_carteira -> 19449.763
B34: PERFIL | C34: Conservador
B35: VALOR A SER INVESTIDO POR MÊS | C35: =aporte -> 500
B37: TIPO DE FII | C37: PERCENTUAL SUGERIDO | D37: VALORES
B38: PAPEL | C38: =VLOOKUP($C$34&"-"&B38,Suport!$A$2:$D$20,4,) -> 0.3 | D38: =C38*valor_sugerido -> 150
B39: TIJOLO | C39: =VLOOKUP($C$34&"-"&B39,Suport!$A$2:$D$20,4,) -> 0.5 | D39: =C39*valor_sugerido -> 250
B40: HÍBRIDOS | C40: =VLOOKUP($C$34&"-"&B40,Suport!$A$2:$D$20,4,) -> 0.1 | D40: =C40*valor_sugerido -> 50
B41: FOFs | C41: =VLOOKUP($C$34&"-"&B41,Suport!$A$2:$D$20,4,) -> 0.1 | D41: =C41*valor_sugerido -> 50
B42: DESENVOLVIMENTO | C42: =VLOOKUP($C$34&"-"&B42,Suport!$A$2:$D$20,4,) -> 0 | D42: =C42*valor_sugerido -> 0
B43: HOTELARIAS | C43: =VLOOKUP($C$34&"-"&B43,Suport!$A$2:$D$20,4,) -> 0 | D43: =C43*valor_sugerido -> 0
B44: TOTAL | D44: =SUM(D38:D43) -> 500

Sheet Suport
A2: CHAVE | B2: PERFIL | C2: TIPO DE FII | D2: %
A3: =$B$3&"-"&C3 -> Conservador-PAPEL | B3: Conservador | C3: PAPEL | D3: 0.3
A4: =$B$3&"-"&C4 -> Conservador-TIJOLO | B4: Conservador | C4: TIJOLO | D4: 0.5
A5: =$B$3&"-"&C5 -> Conservador-HÍBRIDOS | B5: Conservador | C5: HÍBRIDOS | D5: 0.1
A6: =$B$3&"-"&C6 -> Conservador-FOFs | B6: Conservador | C6: FOFs | D6: 0.1
A7: =$B$3&"-"&C7 -> Conservador-DESENVOLVIMENTO | B7: Conservador | C7: DESENVOLVIMENTO | D7: 0
A8: =$B$3&"-"&C8 -> Conservador-HOTELARIAS | B8: Conservador | C8: HOTELARIAS | D8: 0
A9: =$B$9&"-"&C9 -> Moderado-PAPEL | B9: Moderado | C9: PAPEL | D9: 0.32
A10: =$B$9&"-"&C10 -> Moderado-TIJOLO | B10: Moderado | C10: TIJOLO | D10: 0.35
A11: =$B$9&"-"&C11 -> Moderado-HÍBRIDOS | B11: Moderado | C11: HÍBRIDOS | D11: 0.08
A12: =$B$9&"-"&C12 -> Moderado-FOFs | B12: Moderado | C12: FOFs | D12: 0.05
A13: =$B$9&"-"&C13 -> Moderado-DESENVOLVIMENTO | B13: Moderado | C13: DESENVOLVIMENTO | D13: 0.1
A14: =$B$9&"-"&C14 -> Moderado-HOTELARIAS | B14: Moderado | C14: HOTELARIAS | D14: 0.1
A15: =$B$15&"-"&C15 -> Agressivo-PAPEL | B15: Agressivo | C15: PAPEL | D15: 0.5
A16: =$B$15&"-"&C16 -> Agressivo-TIJOLO | B16: Agressivo | C16: TIJOLO | D16: 0.1
A17: =$B$15&"-"&C17 -> Agressivo-HÍBRIDOS | B17: Agressivo | C17: HÍBRIDOS | D17: 0.05
A18: =$B$15&"-"&C18 -> Agressivo-FOFs | B18: Agressivo | C18: FOFs | D18: 0.05
A19: =$B$15&"-"&C19 -> Agressivo-DESENVOLVIMENTO | B19: Agressivo | C19: DESENVOLVIMENTO | D19: 0.2
A20: =$B$15&"-"&C20 -> Agressivo-HOTELARIAS | B20: Agressivo | C20: HOTELARIAS | D20: 0.1
